exp_hurst/__init__.py
exp_hurst/exp_hurst.py
exp_hurst-0.0.2.dist-info/METADATA
exp_hurst-0.0.2.dist-info/WHEEL
exp_hurst-0.0.2.dist-info/licenses/LICENSE
exp_hurst-0.0.2.dist-info/RECORD
