Metadata-Version: 2.3
Name: exp_hurst
Version: 0.0.2
Summary: It computes the Hurst exponent of a time series.
Author-email: Igor Jasenovski <igormjsk@gmail.com>
License-File: LICENSE
Classifier: License :: OSI Approved :: MIT License
Classifier: Operating System :: OS Independent
Classifier: Programming Language :: Python :: 3
Requires-Python: >=3.9
